lesion_metrics/__init__.py
lesion_metrics/helper.py
lesion_metrics/metrics.py
lesion_metrics/py.typed
lesion_metrics/typing.py
lesion_metrics/utils.py
lesion_metrics/volume.py
lesion_metrics/cli/__init__.py
lesion_metrics/cli/aggregate.py
lesion_metrics/cli/common.py
lesion_metrics/cli/per_lesion.py
lesion_metrics-0.1.12.dist-info/LICENSE
lesion_metrics-0.1.12.dist-info/METADATA
lesion_metrics-0.1.12.dist-info/WHEEL
lesion_metrics-0.1.12.dist-info/entry_points.txt
lesion_metrics-0.1.12.dist-info/top_level.txt
lesion_metrics-0.1.12.dist-info/RECORD
