Metadata-Version: 2.1
Name: lesion-metrics
Version: 0.1.12
Summary: metrics for evaluating lesion segmentations
Home-page: https://github.com/jcreinhold/lesion-metrics
Author: Jacob Reinhold
Author-email: jcreinhold@gmail.com
License: Apache Software License 2.0
Project-URL: Bug Tracker, https://github.com/jcreinhold/lesion-metrics/issues
Project-URL: Documentation, https://lesion-metrics.readthedocs.io/
Keywords: lesion,metrics,segmentation,mri,ct,pet
Platform: UNKNOWN
Classifier: Development Status :: 4 - Beta
Classifier: Intended Audience :: Developers
Classifier: License :: OSI Approved :: Apache Software License
Classifier: Natural Language :: English
Classifier: Programming Language :: Python :: 3
Classifier: Programming Language :: Python :: 3 :: Only
Classifier: Programming Language :: Python :: 3.8
Classifier: Programming Language :: Python :: 3.9
Classifier: Programming Language :: Python :: Implementation :: CPython
Classifier: Typing :: Typed
Requires-Python: >=3.8
License-File: LICENSE
Requires-Dist: pillow (>=9.0.0)
Requires-Dist: scikit-image (<1,>=0.18)
Requires-Dist: scipy (<2,>=1.6)
Provides-Extra: cli
Requires-Dist: numpy (<2.0,>=1.21) ; extra == 'cli'
Requires-Dist: nibabel (<4,>=3) ; extra == 'cli'
Requires-Dist: pandas (<2,>=1.3.5) ; extra == 'cli'
Requires-Dist: pydicom (<3,>=2) ; extra == 'cli'
Requires-Dist: pymedio (<1,>=0.1.8) ; extra == 'cli'
Requires-Dist: SimpleITK (<3,>=2.1.0) ; extra == 'cli'
